pyautoscan/__init__.py
pyautoscan/advanced_scan.py
pyautoscan/basic_scan.py
pyautoscan/scanner_info.py
pyautoscan-1.0.0.dist-info/licenses/LICENSE
tests/__init__.py
tests/test_basic_scan.py
pyautoscan-1.0.0.dist-info/METADATA
pyautoscan-1.0.0.dist-info/WHEEL
pyautoscan-1.0.0.dist-info/entry_points.txt
pyautoscan-1.0.0.dist-info/top_level.txt
pyautoscan-1.0.0.dist-info/RECORD
