Metadata-Version: 2.4
Name: pyautoscan
Version: 1.0.0
Summary: A Python-based Windows scanning automation tool for printer/scanner devices using WIA
Home-page: https://github.com/Pandiyarajk/pyautoscan
Author: Pandiyaraj Karuppasamy
Author-email: Pandiyaraj Karuppasamy <pandiyarajk@live.com>
Maintainer-email: Pandiyaraj Karuppasamy <pandiyarajk@live.com>
License: MIT
Project-URL: Homepage, https://github.com/Pandiyarajk/pyautoscan
Project-URL: Documentation, https://github.com/Pandiyarajk/pyautoscan#readme
Project-URL: Repository, https://github.com/Pandiyarajk/pyautoscan
Project-URL: Bug Tracker, https://github.com/Pandiyarajk/pyautoscan/issues
Project-URL: Source Code, https://github.com/Pandiyarajk/pyautoscan
Keywords: scanner,scanning,windows,wia,automation,printer,document,image,pdf
Platform: Windows
Classifier: Development Status :: 5 - Production/Stable
Classifier: Intended Audience :: Developers
Classifier: Intended Audience :: End Users/Desktop
Classifier: License :: OSI Approved :: MIT License
Classifier: Operating System :: Microsoft :: Windows
Classifier: Programming Language :: Python :: 3
Classifier: Programming Language :: Python :: 3.8
Classifier: Programming Language :: Python :: 3.9
Classifier: Programming Language :: Python :: 3.10
Classifier: Programming Language :: Python :: 3.11
Classifier: Programming Language :: Python :: 3.13
Classifier: Topic :: Multimedia :: Graphics :: Capture :: Scanners
Classifier: Topic :: Scientific/Engineering :: Image Processing
Classifier: Topic :: Software Development :: Libraries :: Python Modules
Classifier: Topic :: System :: Hardware
Classifier: Topic :: Utilities
Requires-Python: >=3.7
License-File: LICENSE
Requires-Dist: pywin32>=306
Requires-Dist: Pillow>=9.0.0
Requires-Dist: powerlogger>=0.1.0
Provides-Extra: dev
Requires-Dist: pytest>=7.0.0; extra == "dev"
Requires-Dist: black>=22.0.0; extra == "dev"
Requires-Dist: isort>=5.0.0; extra == "dev"
Requires-Dist: flake8>=4.0.0; extra == "dev"
Requires-Dist: mypy>=1.0.0; extra == "dev"
Requires-Dist: bandit>=1.7.0; extra == "dev"
Requires-Dist: pyinstaller>=5.0.0; extra == "dev"
Dynamic: author
Dynamic: home-page
Dynamic: license-file
Dynamic: platform
Dynamic: requires-python
